{
	"1":[
		{
			"type":"changeMap",
			"mapID":"17",
			"x":36,
			"y":10
		}
	],
	"2":[
		{
			"type":"sequence",
			"action":[
				{
					"type":"stopBGM",
					"file":"NORTH.mp3"
				},
				{
					"type":"spawn",
					"action":[
						{
							"type":"charaMsg",
							"text":["あがあああああああああ！！"],
							"charaID":"9",
							"name":"？？？",
							"option":"reaction"
						},
						{
							"type":"playSE",
							"file":"agaa.mp3"
						}
					]
				},
				{
					"type":"charaMsg",
					"text":["アイツだ！"],
					"charaID":"0",
					"imgID":"3",
					"option":"reaction"
				},
				{
					"type":"playBGM",
					"file":"7haizuri.mp3"
				},
				{
					"type":"already"
				},
				{
					"type":"countDown",
					"second":3.0,
					"condition":[
						{
							"equip":["157"]
						}
					],
					"true":[
						{
							"type":"sequence",
							"action":[
								{
									"type":"stopCount"
								},
								{
									"type":"fadeout"
								},
								{
									"type":"charaMsg",
									"talk":[
										{
											"text":["隠れる場所がない！？"],
											"charaID":"0",
											"imgID":"3"
										},
										{
											"text":["仕方がない！！\nこのダンボールで身を隠そう！"],
											"charaID":"0",
											"imgID":"2"
										}
									]
								},
								{
									"type":"playBGM",
									"file":"kodou.mp3",
									"volume":20.0
								},
								{
									"type":"wait",
									"time":5.0
								},
								{
									"type":"playSE",
									"file":"agaa.mp3"
								},
								{
									"type":"wait",
									"time":5.0
								},
								{
									"type":"stopBGM",
									"file":"kodou.mp3"
								},
								{
									"type":"fadein"
								},
								{
									"type":"stopBGM",
									"file":"7haizuri.mp3"
								},
								{
									"type":"charaMsg",
									"text":["もう・・・行ったかな？"],
									"charaID":"0",
									"imgID":"1"
								},
								{
									"type":"playBGM",
									"file":"NORTH.mp3"
								},
								{
									"type":"already",
									"event":["20","20"]
								}
							]
						}
					],
					"false":[
						{
							"type":"sequence",
							"action":[
								{
									"type":"charaMsg",
									"text":["そんな！\nどこにも隠れられそうな場所がない！"],
									"charaID":"0",
									"imgID":"3",
									"option":"reaction"
								},
								{
									"type":"createEnemy",
									"x":9,
									"y":25,
									"enemyID":"143",
									"charaID":"8",
									"movePattern":"5",
									"speed":10.0
								}
							]
						}
					]
				}
			]
		}
	],
	"3":[
		{
			"type":"spawn",
			"action":[
				{
					"type":"getItem",
					"itemID":"1518",
					"name":"図書室の鍵"
				},
				{
					"type":"removeChara",
					"objID":"1918"
				},
				{
					"type":"already"
				}
			]
		}
	],
	"4":[
		{
			"type":"if",
			"condition":[
				{
					"event":["20","3"]
				}
			],
			"action":[
				{
					"type":"removeChara",
					"objID":"1918"
				}
			]
		}
	],
	"5":[
		{
			"type":"systemMsg",
			"text":["調理器具が乱雑に置いてある"]
		}
	],
	"6":[
		{
			"type":"systemMsg",
			"text":["木箱が置いてある\n開きそうにない・・・"]	
		}
	],
	"7":[
		{
			"type":"systemMsg",
			"text":["半開きの救急箱だ\n中身はない"]
		}
	],
	"8":[
		{
			"type":"systemMsg",
			"text":["最近まで使っていた形跡がある"]
		}
	],
	"9":[
		{
			"type":"systemMsg",
			"text":["何も入っていない・・・"]
		}
	],
	"10":[
		{
			"type":"systemMsg",
			"text":["大量のダンボールが置いてある"]
		}
	],
	"11":[
		{
			"type":"systemMsg",
			"text":["中はカラッポだ・・・"]
		}
	],
	"12":[
		{
			"type":"if",
			"condition":[
				{
					"Nevent":["20","16"],
					"event":["34","8"]
				}
			],
			"action":[
				{
					"type":"getItem",
					"itemID":"1529",
					"name":"目玉焼きリング"
				},
				{
					"type":"removeChara",
					"objID":"1929"
				},
				{
					"type":"already",
					"event":["20","16"]
				}
			]
		},
		{
			"type":"if",
			"condition":[
				{
					"event":["20","16"]
				},
				{
					"Nevent":["34","8"]
				}
			],
			"action":[
				{
					"type":"systemMsg",
					"text":["大量のダンボールの中にはなぜか\n目玉焼き専用の焼き器が沢山入っている"]
				}
			]
		}
	],
	"13":[
		{
			"type":"if",
			"condition":[
				{
					"event":["20","16"]
				},
				{
					"Nevent":["34","8"]
				}
			],
			"action":[
				{
					"type":"removeChara",
					"objID":"1929"
				}
			]
		}
	],
	"16":"12のアイテムとった用",
	"19":[
		{
			"type":"if",
			"condition":[
				{
					"event":["20","2"],
					"Nevent":["20","20"]
				}
			],
			"action":[		
				{
					"type":"charaWalk",
					"objID":"hero",
					"direction":"UP",
					"steps":1.0,
					"option":"back"
				}
			]
		}
	],
	"20":"ダンボールに隠れたかどうかチェック用"
}