{
	"1":[
		{
		    "type":"setAmbient",
		    "ambient":"night"
		},
		{
			"type":"if",
			"condition":[
				{
					"flg":["57","5",0]
				}
			],
			"action":[
				{
					"type":"removeLayer",
					"layer":"water"
				},
				{
					"type":"removeLayer",
					"layer":"plate"
				}
			]
		},
		{
			"type":"if",
			"condition":[
				{
					"flg":["57","5",1]
				}
			],
			"action":[
				{
					"type":"removeObject",
					"objID":"181"
				},
				{
					"type":"removeObject",
					"objID":"182"
				}
			]
		},
		{
			"type":"if",
			"condition":[
				{
					"event":["58","4"]
				}
			],
			"action":[
				{
					"type":"removeObject",
					"objID":"183"
				}
			]
		}
	],
	"2":[
		{
			"type":"changeMap",
			"mapID":"56",
			"x":30,
			"y":7
		}
	],
	"3":[
		{
			"type":"sequence",
			"action":[
				{
					"type":"playSE",
					"file":"iron_door.mp3"
				},
				{
					"type":"removeLayer",
					"layer":"door1"
				},
				{
					"type":"wait",
					"time":0.2
				},
				{
					"type":"removeLayer",
					"layer":"door2"
				},
				{
					"type":"wait",
					"time":0.2
				},
				{
					"type":"removeLayer",
					"layer":"door3"
				},
				{
					"type":"wait",
					"time":0.2
				},
				{
					"type":"changeMap",
					"mapID":"59",
					"x":9,
					"y":19
				}
			]
		}
	],
	"4":[
		{
			"type":"if",
			"condition":[
				{
					"Nitem":"158"
				}
			],
			"action":[
				{
					"type":"playSE",
					"file":"door_unopen.mp3"
				},
				{
					"type":"systemMsg",
					"text":["鍵がかかっている・・・"]
				}
			]
		},
		{
			"type":"if",
			"condition":[
				{
					"item":"158"
				}
			],
			"action":[
				{
					"type":"sequence",
					"action":[
						{
							"type":"spawn",
							"action":[
								{
									"type":"playSE",
									"file":"door_keyopen.mp3"
								},
								{
									"type":"removeObject",
									"objID":"183"
								},
								{
									"type":"removeItem",
									"itemID":"158"
								},
								{
									"type":"systemMsg",
									"text":["下水道管理室の鍵を使った"]
								}
							]
						},
						{
							"type":"already"
						}
					]
				}
			]
		}
	]
}